pyraklib/Binary.py
pyraklib/PyRakLib.py
pyraklib/Queue.py
pyraklib/__init__.py
pyraklib/protocol/ACK.py
pyraklib/protocol/AcknowledgePacket.py
pyraklib/protocol/ADVERTISE_SYSTEM.py
pyraklib/protocol/CLIENT_CONNECT_DataPacket.py
pyraklib/protocol/CLIENT_DISCONNECT_DataPacket.py
pyraklib/protocol/CLIENT_HANDSHAKE_DataPacket.py
pyraklib/protocol/DataPacket.py
pyraklib/protocol/DataPackets.py
pyraklib/protocol/EncapsulatedPacket.py
pyraklib/protocol/NACK.py
pyraklib/protocol/OPEN_CONNECTION_REPLY_1.py
pyraklib/protocol/OPEN_CONNECTION_REPLY_2.py
pyraklib/protocol/OPEN_CONNECTION_REQUEST_1.py
pyraklib/protocol/OPEN_CONNECTION_REQUEST_2.py
pyraklib/protocol/Packet.py
pyraklib/protocol/PING_DataPacket.py
pyraklib/protocol/PONG_DataPacket.py
pyraklib/protocol/SERVER_HANDSHAKE_DataPacket.py
pyraklib/protocol/UNCONNECTED_PING.py
pyraklib/protocol/UNCONNECTED_PING_OPEN_CONNECTIONS.py
pyraklib/protocol/UNCONNECTED_PONG.py
pyraklib/protocol/__init__.py
pyraklib/server/PyRakLibServer.py
pyraklib/server/ServerHandler.py
pyraklib/server/ServerInstance.py
pyraklib/server/Session.py
pyraklib/server/SessionManager.py
pyraklib/server/UDPServerSocket.py
pyraklib/server/__init__.py
PyRakLib-1.0.15b1.dist-info/DESCRIPTION.rst
PyRakLib-1.0.15b1.dist-info/METADATA
PyRakLib-1.0.15b1.dist-info/metadata.json
PyRakLib-1.0.15b1.dist-info/RECORD
PyRakLib-1.0.15b1.dist-info/top_level.txt
PyRakLib-1.0.15b1.dist-info/WHEEL
