Metadata-Version: 2.0
Name: PyRakLib
Version: 1.0.15b1
Summary: A port of the PHP RakLib library to Python.
Home-page: https://github.com/jython234/PyRakLib
Author: jython234
Author-email: jython234@blockserver.org
License: GPL V3
Keywords: PHP library MCPE minecraft raknet raklib networking Python
Platform: UNKNOWN
Classifier: Development Status :: 3 - Alpha
Classifier: Intended Audience :: Developers
Classifier: License :: OSI Approved :: GNU General Public License v3 or later (GPLv3+)
Classifier: Programming Language :: Python :: 3 :: Only
Classifier: Topic :: Software Development :: Libraries
Requires: requests
